{
  "users": [
    {
      "id": 5,
      "name": "Bram Marshman",
      "emailAddress": "bmarshman4@smugmug.com",
      "address": "000 Maryland Road"
    },
    {
      "id": 65,
      "name": "Aubrie Whitear",
      "emailAddress": "awhitear1s@biglobe.ne.jp",
      "address": "0495 Fieldstone Point"
    },
    {
      "id": 78,
      "name": "Euphemia Simeonov",
      "emailAddress": "esimeonov25@twitpic.com",
      "address": "90 Porter Place"
    },
    {
      "id": 87,
      "name": "Carlita Godsmark",
      "emailAddress": "cgodsmark2e@bigcartel.com",
      "address": "9216 Mcbride Avenue"
    },
    {
      "id": 88,
      "name": "Norbie Gunney",
      "emailAddress": "ngunney2f@unblog.fr",
      "address": "908 Miller Trail"
    },
    {
      "id": 89,
      "name": "Bald Fazackerley",
      "emailAddress": "bfazackerley2g@icio.us",
      "address": "00 Mosinee Alley"
    },
    {
      "id": 90,
      "name": "Fergus Binfield",
      "emailAddress": "fbinfield2h@slashdot.org",
      "address": "0 Schmedeman Street"
    },
    {
      "id": 91,
      "name": "Xaviera Dewi",
      "emailAddress": "xdewi2i@cmu.edu",
      "address": "1785 Fairfield Street"
    },
    {
      "id": 92,
      "name": "Scottie Hamsson",
      "emailAddress": "shamsson2j@paginegialle.it",
      "address": "49 Knutson Avenue"
    },
    {
      "id": 93,
      "name": "Marion Curtin",
      "emailAddress": "mcurtin2k@jimdo.com",
      "address": "1831 Pepper Wood Place"
    },
    {
      "id": 94,
      "name": "Brett Duffill",
      "emailAddress": "bduffill2l@stumbleupon.com",
      "address": "80 Prairieview Court"
    },
    {
      "id": 95,
      "name": "Hilly Didball",
      "emailAddress": "hdidball2m@fda.gov",
      "address": "1885 Pawling Junction"
    },
    {
      "id": 96,
      "name": "Meryl Garrat",
      "emailAddress": "mgarrat2n@facebook.com",
      "address": "58860 Derek Plaza"
    },
    {
      "id": 97,
      "name": "Ernaline Pagram",
      "emailAddress": "epagram2o@yellowpages.com",
      "address": "6879 Holmberg Road"
    },
    {
      "id": 98,
      "name": "Karie Dundridge",
      "emailAddress": "kdundridge2p@mlb.com",
      "address": "1376 Autumn Leaf Alley"
    },
    {
      "id": 99,
      "name": "Wynny Quest",
      "emailAddress": "wquest2q@edublogs.org",
      "address": "00656 High Crossing Park"
    },
    {
      "id": 100,
      "name": "Georgiana Sibbons",
      "emailAddress": "gsibbons2r@purevolume.com",
      "address": "36757 Raven Park"
    }
  ]
}